mixedbread_ai/__init__.py
mixedbread_ai/client.py
mixedbread_ai/core/__init__.py
mixedbread_ai/core/api_error.py
mixedbread_ai/core/client_wrapper.py
mixedbread_ai/core/datetime_utils.py
mixedbread_ai/core/file.py
mixedbread_ai/core/http_client.py
mixedbread_ai/core/jsonable_encoder.py
mixedbread_ai/core/pydantic_utilities.py
mixedbread_ai/core/query_encoder.py
mixedbread_ai/core/remove_none_from_dict.py
mixedbread_ai/core/request_options.py
mixedbread_ai/environment.py
mixedbread_ai/errors/__init__.py
mixedbread_ai/errors/bad_request_error.py
mixedbread_ai/errors/forbidden_error.py
mixedbread_ai/errors/internal_server_error.py
mixedbread_ai/errors/not_found_error.py
mixedbread_ai/errors/too_many_requests_error.py
mixedbread_ai/errors/unauthorized_error.py
mixedbread_ai/errors/unprocessable_entity_error.py
mixedbread_ai/types/__init__.py
mixedbread_ai/types/bad_request_error_body.py
mixedbread_ai/types/data.py
mixedbread_ai/types/embedding.py
mixedbread_ai/types/embedding_item.py
mixedbread_ai/types/embeddings_request_encoding_format.py
mixedbread_ai/types/embeddings_response.py
mixedbread_ai/types/embeddings_response_encoding_format.py
mixedbread_ai/types/encoding_format.py
mixedbread_ai/types/forbidden_error_body.py
mixedbread_ai/types/input.py
mixedbread_ai/types/internal_error.py
mixedbread_ai/types/invalid_matryoshka_dimensions_error.py
mixedbread_ai/types/invalid_matryoshka_model_error.py
mixedbread_ai/types/model_not_found_error.py
mixedbread_ai/types/multi_modal_input.py
mixedbread_ai/types/multiple_encodings_embedding.py
mixedbread_ai/types/multiple_encodings_embedding_item.py
mixedbread_ai/types/mxbai_api_error.py
mixedbread_ai/types/mxbai_api_error_details.py
mixedbread_ai/types/not_found_error_body.py
mixedbread_ai/types/object_type.py
mixedbread_ai/types/query.py
mixedbread_ai/types/ranked_document.py
mixedbread_ai/types/reranking_response.py
mixedbread_ai/types/text_document.py
mixedbread_ai/types/too_many_requests_error_body.py
mixedbread_ai-2.2.5.dist-info/LICENSE.md
mixedbread_ai-2.2.5.dist-info/METADATA
mixedbread_ai-2.2.5.dist-info/WHEEL
mixedbread_ai-2.2.5.dist-info/RECORD
