Metadata-Version: 2.1
Name: mixedbread-ai
Version: 2.2.5
Summary: mixedbread ai (https://www.mixedbread.ai)
Home-page: https://github.com/mixedbread-ai/python-sdk.git
License: Apache-2.0
Keywords: Embeddings,NLP,mixedbread.ai
Author: mixedbread.ai
Author-email: support@mixedbread.ai
Requires-Python: >=3.8,<4.0
Classifier: License :: OSI Approved :: Apache Software License
Classifier: Programming Language :: Python :: 3
Classifier: Programming Language :: Python :: 3.8
Classifier: Programming Language :: Python :: 3.9
Classifier: Programming Language :: Python :: 3.10
Classifier: Programming Language :: Python :: 3.11
Classifier: Programming Language :: Python :: 3.12
Requires-Dist: httpx (>=0.21.2)
Requires-Dist: pydantic (>=1.9.2)
Requires-Dist: typing_extensions (>=4.0.0)
Project-URL: Repository, https://github.com/mixedbread-ai/python-sdk.git
